Metadata-Version: 2.4
Name: hwc-bgrx-8888-ndarray-to-chw-rgb-0-1-tensor
Version: 0.1.0a0
Summary: Convert an HWC BGR 888 or BGRX 8888 NumPy ndarray to a CHW RGB PyTorch tensor, with pixel values normalized to `[0, 1]` and the alpha/unused channel discarded.
Author-email: Jifeng Wu <jifengwu2k@gmail.com>
License-Expression: MIT
Project-URL: Homepage, https://github.com/jifengwu2k/hwc-bgrx-8888-ndarray-to-chw-rgb-0-1-tensor
Project-URL: Bug Tracker, https://github.com/jifengwu2k/hwc-bgrx-8888-ndarray-to-chw-rgb-0-1-tensor/issues
Classifier: Programming Language :: Python :: 2
Classifier: Programming Language :: Python :: 3
Classifier: Operating System :: OS Independent
Requires-Python: >=2
License-File: LICENSE
Requires-Dist: numpy
Requires-Dist: torch
Dynamic: license-file
